{
	"configurations" : 
	[
		{
			"directories" : 
			[
				{
					"build" : ".",
					"jsonFile" : "directory-.-Debug-f5ebdc15457944623624.json",
					"minimumCMakeVersion" : 
					{
						"string" : "3.25"
					},
					"projectIndex" : 0,
					"source" : ".",
					"targetIndexes" : 
					[
						0
					]
				}
			],
			"name" : "Debug",
			"projects" : 
			[
				{
					"directoryIndexes" : 
					[
						0
					],
					"name" : "algoritmo_greedy",
					"targetIndexes" : 
					[
						0
					]
				}
			],
			"targets" : 
			[
				{
					"directoryIndex" : 0,
					"id" : "algoritmo_greedy::@6890427a1f51a3e7e1df",
					"jsonFile" : "target-algoritmo_greedy-Debug-66bd1994f7821ce0f169.json",
					"name" : "algoritmo_greedy",
					"projectIndex" : 0
				}
			]
		}
	],
	"kind" : "codemodel",
	"paths" : 
	{
		"build" : "/home/flo/Desktop/ALG/ALG_PRACTICA_3/algoritmo_greedy/cmake-build-debug",
		"source" : "/home/flo/Desktop/ALG/ALG_PRACTICA_3/algoritmo_greedy"
	},
	"version" : 
	{
		"major" : 2,
		"minor" : 4
	}
}
